kvaser/__about__.py
kvaser/__init__.py
kvaser/__main__.py
kvaser/__utils__.py
kvaser/blob_storage.py
kvaser/dag.py
kvaser/data.py
kvaser/dist.py
kvaser/reload.py
kvaser/data/d.csv.gz
kvaser/data/surgunit.csv.gz
kvaser/timeseries/__init__.py
kvaser/timeseries/ts.py
kvaser-0.1.7.data/scripts/mproc
kvaser-0.1.7.dist-info/LICENSE
kvaser-0.1.7.dist-info/METADATA
kvaser-0.1.7.dist-info/WHEEL
kvaser-0.1.7.dist-info/top_level.txt
kvaser-0.1.7.dist-info/RECORD
