Metadata-Version: 2.1
Name: kvaser
Version: 0.1.7
Summary: Various utility functions.
Home-page: https://github.com/kkholst/kvaser
Author: Klaus Kähler Holst
Author-email: klaus@holst.it
License: Apache Software License
Classifier: Programming Language :: Python :: 3
Classifier: Programming Language :: C++
Classifier: Intended Audience :: Developers
Classifier: Topic :: Scientific/Engineering :: Mathematics
Classifier: License :: OSI Approved :: Apache Software License
Classifier: Operating System :: OS Independent
License-File: LICENSE
Requires-Dist: azure-storage-blob (>=12.0)
Requires-Dist: datetime
Requires-Dist: networkx
Requires-Dist: numpy (>=1.15)
Requires-Dist: pandas (>=1.0.3)
Requires-Dist: patsy (>=0.5.0)
Requires-Dist: Pillow
Requires-Dist: plotly (>=5.1.0)
Requires-Dist: pytz
Requires-Dist: pydot
Requires-Dist: rich
Requires-Dist: scikit-learn (>=1.1.0)
